swagger_gen/__init__.py
swagger_gen/swagger.py
swagger_gen/lib/__init__.py
swagger_gen/lib/constants.py
swagger_gen/lib/dependency.py
swagger_gen/lib/endpoint.py
swagger_gen/lib/metadata.py
swagger_gen/lib/schema.py
swagger_gen/lib/security.py
swagger_gen/lib/utils.py
swagger_gen/lib/wrappers.py
swagger_gen/resources/__init__.py
swagger_gen/resources/swagger.pkl
swagger_gen-0.1.2.dist-info/LICENSE
swagger_gen-0.1.2.dist-info/METADATA
swagger_gen-0.1.2.dist-info/WHEEL
swagger_gen-0.1.2.dist-info/top_level.txt
swagger_gen-0.1.2.dist-info/RECORD
