Metadata-Version: 2.1
Name: swagger-gen
Version: 0.1.2
Summary: Swagger UI for Flask apps
Author: Dan Leonard
Author-email: dcl525@gmail.com
Keywords: python,swagger-gen
Classifier: Development Status :: 3 - Alpha
Classifier: Programming Language :: Python :: 3
Classifier: Operating System :: MacOS :: MacOS X
Classifier: Operating System :: Microsoft :: Windows
Requires-Python: >=3.9.0
License-File: LICENSE
Requires-Dist: flask
